# 1. 前言

`JVM`的内存可分为几块区域，相关概念参见[方法区.md][method-area]。
在学习的过程中经常还会听到**常量池**这一术语，有必要知道常量池在`JVM`中的地位和分类，以及它和其他内存区的关系。

在探讨常量池的类型之前需要明白什么是常量。
 - 用`final`修饰的成员变量表示常量，值一旦给定就无法改变。
 - `final`修饰的变量有三种：静态变量、实例变量和局部变量，分别表示三种类型的常量。
 
在`JVM`的内存分配中，总共有三种常量池<sup id="a1">[\[1\]](#f1)</sup>：
 - `class`文件常量池（class constant pool）
 - 运行时常量池（runtime constant pool）
 - 全局字符串池（string pool，也叫做 string literal pool）

# 2. class 文件常量池

## 2.1 概念

`class`文件中除了包含类的版本、字段、方法、接口等描述信息外，还有一项信息就是常量池，
用于存放编译器生成的各种字面量(Literal)和符号引用(Symbolic References)。
字面量比较接近`Java`语言层面常量的概念，如文本字符串、被声明为`final`的常量值等。符号引用则属于编译原理方面的概念，
包括了如下三种类型的常量：
 - 类和接口的全限定名：例如对于`String`这个类，它的全限定名就是`java/lang/String`，将类名中原来的"."替换为"/"得到。
 - 字段的名称和描述符：所谓字段就是类或者接口中声明的变量，包括类级别变量（`static`)和实例级的变量。
 - 方法的名称和描述符：所谓描述符就相当于方法的参数类型+返回值类型。
                     
常量池的每一项常量都是一个表，一共有如下表所示的 11 种各不相同的表结构数据，这每个表开始的第一位都是一个字节的标志位（取值 1-12），
代表当前这个常量属于哪种常量类型：

![class 常量池结构][class]

每种不同类型的常量类型具有不同的结构，具体的结构本文就先不叙述了，本文着重区分这三个常量池的概念。
读者若想深入了解每种常量类型的数据结构可以查看《深入理解java虚拟机》第六章的内容。

## 2.2 例子

为了方便说明，我们写个简单的类：
```java
package JavaBasicKnowledge;

class JavaBean {
    private int value = 1;
    public String s = "abc";
    public final static int f = 0x101;

    public void setValue(int v){
        final int temp = 3;
        this.value = temp + v;
    }

    public int getValue(){
        return value;
    }
}
```

在控制台输入`javac JavaBean.java`进行编译，然后输入`javap -verbose JavaBean`查看其编译后的`class`文件如下：
```java
class JavaBasicKnowledge.JavaBean
  minor version: 0
  major version: 52
  flags: ACC_SUPER
Constant pool:
   #1 = Methodref          #6.#29         // java/lang/Object."<init>":()V
   #2 = Fieldref           #5.#30         // JavaBasicKnowledge/JavaBean.value:I
   #3 = String             #31            // abc
   #4 = Fieldref           #5.#32         // JavaBasicKnowledge/JavaBean.s:Ljava/lang/String;
   #5 = Class              #33            // JavaBasicKnowledge/JavaBean
   #6 = Class              #34            // java/lang/Object
   #7 = Utf8               value
   #8 = Utf8               I
   #9 = Utf8               s
  #10 = Utf8               Ljava/lang/String;
  #11 = Utf8               f
  #12 = Utf8               ConstantValue
  #13 = Integer            257
  #14 = Utf8               <init>
  #15 = Utf8               ()V
  #16 = Utf8               Code
  #17 = Utf8               LineNumberTable
  #18 = Utf8               LocalVariableTable
  #19 = Utf8               this
  #20 = Utf8               LJavaBasicKnowledge/JavaBean;
  #21 = Utf8               setValue
  #22 = Utf8               (I)V
  #23 = Utf8               v
  #24 = Utf8               temp
  #25 = Utf8               getValue
  #26 = Utf8               ()I
  #27 = Utf8               SourceFile
  #28 = Utf8               StringConstantPool.java
  #29 = NameAndType        #14:#15        // "<init>":()V
  #30 = NameAndType        #7:#8          // value:I
  #31 = Utf8               abc
  #32 = NameAndType        #9:#10         // s:Ljava/lang/String;
  #33 = Utf8               JavaBasicKnowledge/JavaBean
  #34 = Utf8               java/lang/Object
```
我们得到了该`class`文件的版本号、常量池、已经编译后的字节码（这里未列出）。前面已经说过，`class`文件常量池主要存放两大常量：
字面量和符号引用。

### 2.2.1 字面量

字面量接近`java`语言层面的常量概念，主要包括：
 - 文本字符串。也就是`JavaBean.java`中申明的`public String s = "abc";`中的`abc`。
```java
  #9 = Utf8               s
  #3 = String             #31            // abc
  #31 = Utf8              abc
```
 - 用`final`修饰的成员变量，包括静态变量、实例变量和局部变量。
```java
  #11 = Utf8               f
  #12 = Utf8               ConstantValue
  #13 = Integer            257
```

这里需要说明的一点，上面说的存在于常量池的字面量，指的是数据的值，也就是`abc`和`257`。
通过上面对常量池的观察可知这两个字面量是确实存在于常量池的。而对于基本类型数据(或是方法中的局部变量)，
`boolean`、`short`、`int`等采用`bipush`、`sipush`指令加载到操作数栈的不会存在于常量池，
但是对于使用`ldc`指令加载的，是会存在于常量池的。比如大于`int`大于 32767 的字面量、`long`大于 1 或小于 0 的字面量、
`float`, `double`的字面量（除了极个别整数 1、2）都存在于常量池。 

### 2.2.2 符号引用

符号引用主要设涉及编译原理方面的概念，包括下面三类常量:
 - 类和接口的全限定名，也就是`java/lang/String;`这样，将类名中原来的"."替换为"/"得到的，
 主要用于在运行时解析得到类的直接引用。
```java
  #5 = Class              #33            // JavaBasicKnowledge/JavaBean
  #33 = Utf8              JavaBasicKnowledge/JavaBean
```
 - 字段的名称和描述符，字段也就是类或者接口中声明的变量，包括类级别变量和实例级的变量。
```java
  #4 = Fieldref           #5.#32         // JavaBasicKnowledge/JavaBean.value:I
  #5 = Class              #33            // JavaBasicKnowledge/JavaBean
  #32 = NameAndType       #7:#8          // value:I

  #7 = Utf8               value
  #8 = Utf8               I

  //这两个是局部变量，只保留字段名称
  #23 = Utf8               v
  #24 = Utf8               temp
```
可以看到，对于方法中的局部变量，`class`文件的常量池仅仅保存字段名。
 - 方法中的名称和描述符，也即参数类型+返回值
```java
  #21 = Utf8               setValue
  #22 = Utf8               (I)V

  #25 = Utf8               getValue
  #26 = Utf8               ()I
```

# 3. 运行时常量池

运行时常量池是方法区的一部分。当`Java`文件被编译成`class`文件之后，会生成`class`文件常量池。
`JVM`在执行某个类的时候，必须经过加载、链接、初始化，而链接又包括验证、准备、解析（resolve）三个阶段。
在第一步加载时需要完成：
1. 通过一个类的全限定名来获取此类的二进制字节流
2. 将这个字节流所代表的静态存储结构转化为方法区的运行时数据结构
3. 在内存中生成一个类对象，代表加载的这个类，这个对象是`PackagePath.ClassName`，它作为方法区这个类的各种数据访问的入口。
类对象和普通对象是不同的，类对象是在类加载的时候完成的，是`JVM`创建的并且是单例的，作为这个类和外界交互的入口，
而普通的对象一般是在调用`new`之后创建。

当类加载到内存中后，`JVM`就会将`class`文件常量池中的内容存放到运行时常量池中。需要的注意的是，运行时常量池是全局共享的，
多个类共用一个运行时常量池。并且`class`文件常量池中多个相同的字符串在运行时常量池只会存在一份。解析的过程会去查询全局字符串常量池，
以保证运行时常量池所引用的字符串与全局字符串常量池中所引用的是一致的。

运行时常量池的作用是存储`class`文件常量池中的符号信息，运行时常量池中保存着一些`class`文件中描述的符号引用，
同时在类的解析阶段还会将这些符号引用翻译成直接引用（直接指向实例对象的指针，内存地址），
翻译出来的直接引用也是存储在运行时常量池中。

运行时常量池相对于`class`常量池一大特征就是具有动态性，`java`规范并不要求常量只能在运行时才产生，
也就是说运行时常量池的内容并不全部来自`class`常量池，在运行时可以通过代码生成常量并将其放入运行时常量池中，
这种特性被用的最多的就是`String.intern()`。
 
# 4. 全局字符串常量池

## 4.1 所处位置

 - 在`JDK6.0`及之前版本，全局字符串常量池是放在`Perm Gen`区(也就是方法区)中，此时全局字符串常量池中存储的是对象。
 - 在`JDK7.0`版本，全局字符串常量池被移到了堆中了，此时全局字符串常量池存储的是引用。
 - 在`JDK8.0`中，永久代（方法区）被元空间取代了，全局字符串常量池继续存在于堆中。
 
## 4.2 概念和底层原理

在`HotSpot VM`里实现的字符串池功能的是一个`StringTable`类，它是一个`Hash`表，默认值大小长度是 1009。
在字符串常量池中维护的是字符串实例的引用，底层`C++`实现就是一个`HashTable`。这些被维护的引用所指的字符串实例，
被称作”被驻留的字符串”或“interned string”，也就是通常所说的“进入了字符串常量池的字符串”。
这个`StringTable`在每个`HotSpot VM`的实例里只有一份，被所有的类共享。

`StringTable`是个纯运行时的结构，而且是惰性（lazy）维护的。注意它只存储对`String`实例的引用，而不存储`String`对象的内容，
根据这个引用可以得到具体的`String`对象。

在`JDK6.0`中，`StringTable`的长度是固定的，就是 1009，因此如果放入`string pool`中的`String`非常多，就会造成`hash`冲突，
导致链表过长（`JDK6.0`的`HashSet`采用拉链法构造），当调用`String.intern()`方法时会需要到链表上一个一个找，
从而导致性能大幅度下降。

在`JDK7.0`中，`StringTable`的长度可以通过参数指定：
```
-XX:StringTableSize=66666
```

## 4.3 例子
```java
String s1 = "Hello";
String s2 = "Hello";
String s3 = "Hel" + "lo";
String s4 = "Hel" + new String("lo");
String s5 = new String("Hello");
String s7 = "H";
String s8 = "ello";
String s9 = s7 + s8;

System.out.println(s1 == s2);  // true
System.out.println(s1 == s3);  // true
System.out.println(s1 == s4);  // false
System.out.println(s1 == s5);  // false
System.out.println(s1 == s9);  // false
```
1. `s1`和`s2`都是字面量，`"Hello"`在编译时会直接进入`class`文件常量池中；当运行期间在全局字符串常量池中会保存它的一个引用。
实际上最终还是要在堆上创建一个`"Hello"`对象，这个后面会讲。`s1`和`s2`引用的是同一个对象，因此相等。
2. `s3`虽然由两个字面量拼接，看起来会创建新的对象，但由于编译器[常量折叠][constant-fold]的效果，它仍然会引用同一个`"Hello"`对象。
3. `s4`和`s5`由于创建了对象，此时它和全局字符串常量池中的`"Hello"`对象不是同一个了。
4. `s9`看起来可以进行常量折叠，实际上不可以，因为`s7`和`s8`是两个变量而非常量，所以编译器在这种不确定的情况下不会进行常量折叠，
因此`s1`和`s9`引用的是不同的对象。

测试代码可在[StringTest.java][test]中找到。

## 4.4 探究 String 字面量何时进入全局字符串常量池

### 4.4.1 ldc 指令和 lazy resolve

前面我们提到过`String`字面量是先存在于`class`文件常量池，然后链接-解析的过程中会去查询全局字符串常量池，
以保证运行时常量池所引用的字符串与全局字符串常量池中所引用的是一致的。这个步骤会将`String`字面量加入到全局字符串常量池。

具体来说，是在执行`ldc`指令时，该指令表示将基本类型或`String`常量从常量池推送至栈顶。

`JVM`规范里`class`文件常量池项的类型，有两种东西：`CONSTANT_Utf8_info`和`CONSTANT_String_info`。

在`HotSpot VM`中，运行时常量池里，`CONSTANT_Utf8_info`可以表示`class`文件的方法、字段等等，其结构如下：

![CONSTANT_Utf8_info 结构][utf8-info]

首先是 1 个字节的`tag`,表示这是一个`CONSTANT_Utf8_info`结构的常量，然后是两个字节的`length`，表示要储存字节的长度，
之后是一个`byte`数组，表示真正的储存的`length`个长度的字符串。这里需要注意的是，`u1`只是代表这里有一个`byte`类型的数组，
而这个数组的长度当然可以远远大于一个字节。当然，由于`CONSTANT_Utf8_info`结构只能用`u2`即两个字节来表示长度，
因此长度的最大值为 65535。

`CONSTANT_String_info`是`String`常量的类型，但它并不直接持有`String`常量的内容，而是只持有一个`index`，
这个`index`所指定的另一个常量池项必须是一个`CONSTANT_Utf8_info`类型的常量，这里才真正持有字符串的内容：

![CONSTANT_String_info 结构][string-info]

`CONSTANT_Utf8_info`会在类加载的过程中就全部创建出来，而`CONSTANT_String_info`则是`lazy resolve`的，
在第一次引用该项的`ldc`指令被第一次执行到的时候才会解析。在尚未解析的时候，
`HotSpot VM`把它的类型叫做`JVM_CONSTANT_UnresolvedString`，内容跟`class`文件里一样只是一个`index`；
等到解析过后这个项的常量类型就会变成最终的`JVM_CONSTANT_String`。

就`HotSpot VM`的实现来说，加载类的时候，那些字符串字面量会进入到当前类的运行时常量池，
不会进入全局的字符串常量池（即在`StringTable`中并没有相应的引用，在堆中也没有对应的对象产生），在执行`ldc`指令时，
触发`lazy resolve`这个动作。

`ldc`字节码在这里的执行语义是：到当前类的运行时常量池（`runtime constant pool`，`HotSpot VM`里是`ConstantPool`+`ConstantPoolCache`）
去查找该`index`对应的项，如果该项尚未解析则解析之，并返回解析后的内容。

在遇到`String`类型常量时，解析的过程如果发现`StringTable`已经有了内容匹配的`String`的引用，则直接返回这个引用，
反之，如果`StringTable`里尚未有内容匹配的`String`实例的引用，则会在`Java`堆里创建一个对应内容的`String`对象，
然后在`StringTable`记录下这个引用，并返回这个引用出去。

可见，`ldc`指令是否需要创建新的`String`实例，全看在第一次执行这一条`ldc`指令时，
`StringTable`是否已经记录了一个对应内容的`String`的引用。

### 4.4.2 例子

`ldc`指令用于将基本类型或`String`常量从常量池推送至栈顶。假设我们有一个如下所示的`Test.java`：
```java
package constant;

public class Test {

    public static void main(String[] args) {
        String s1 = "abc";
        String s2 = "abc";
        String s3 = "xxx";
    }
}
```
在控制台输入`javac Test.java`进行编译，然后输入`javap -verbose Test`查看其编译后的`class`文件如下：
```java
public class constant.Test
  minor version: 0
  major version: 55
  flags: ACC_PUBLIC, ACC_SUPER
Constant pool:
   #1 = Methodref          #5.#14         // java/lang/Object."<init>":()V
   #2 = String             #15            // abc
   #3 = String             #16            // xxx
   #4 = Class              #17            // constant/Test
   #5 = Class              #18            // java/lang/Object
   #6 = Utf8               <init>
   #7 = Utf8               ()V
   #8 = Utf8               Code
   #9 = Utf8               LineNumberTable
  #10 = Utf8               main
  #11 = Utf8               ([Ljava/lang/String;)V
  #12 = Utf8               SourceFile
  #13 = Utf8               Test.java
  #14 = NameAndType        #6:#7          // "<init>":()V
  #15 = Utf8               abc
  #16 = Utf8               xxx
  #17 = Utf8               constant/Test
  #18 = Utf8               java/lang/Object
{
  public constant.Test();
    descriptor: ()V
    flags: ACC_PUBLIC
    Code:
      stack=1, locals=1, args_size=1
         0: aload_0
         1: invokespecial #1                  // Method java/lang/Object."<init>":()V
         4: return
      LineNumberTable:
        line 3: 0

  public static void main(java.lang.String[]);
    descriptor: ([Ljava/lang/String;)V
    flags: ACC_PUBLIC, ACC_STATIC
    Code:
      stack=1, locals=4, args_size=1
         0: ldc           #2                  // String abc
         2: astore_1
         3: ldc           #2                  // String abc
         5: astore_2
         6: ldc           #3                  // String xxx
         8: astore_3
         9: return
      LineNumberTable:
        line 6: 0
        line 7: 3
        line 8: 6
        line 9: 9
}
```
1. `String s1 = "abc";`：解析过程在字符串常量池中发现没有`"abc"`的引用，便在堆中新建一个`"abc"`的对象，
然后`ldc`指令将`"abc"`加载到操作数栈顶，接着用`astore_1`把它赋值给我们定义的局部变量`s1`。
2. `String s2 = "abc";`：解析过程会发现`StringTable`中已经有了`"abc"`对象的引用，则直接返回该引用给`s2`，并不会创建任何对象。
3. `String s3 = "xxx";`：同第一行代码一样，在堆中创建对象，并将该对象的引用存入到`StringTable`，最后返回引用给`s3`。

## 4.5 String.intern() 方法

`String.intern()`方法就是去拿`String`的内容去`StringTable`里查表，如果存在则返回引用，
不存在就把该对象的引用存在`StringTable`表里。
```java
String s1 = new StringBuilder("实例").append("1").toString();
String s2 = "实例1";
System.out.println(s1 == s2);
s1 = s1.intern();
System.out.println(s1 == s2);

String s3 = new StringBuilder("计算机").append("软件").toString();
System.out.println(s3.intern() == s3);

String s4 = new StringBuilder("ja").append("va").toString();
System.out.println(s4.intern() == s4);

String s5 = new String("xyz");
System.out.println(s5.intern() == s5);
```
以上代码，在`JDK6`及以前，`JDK7`及以后的表现时不同的。

1. `JDK6`及以前：常量池在方法区中，也就是在永久代里。`intern`方法会把首次遇到的字符串实例复制到永久代中，
返回的也是这个永久代中字符串实例的引用。
    - `s1`是新创建的对象，`s2`存在于永久代的常量池中，因此第一个输出为`false`；当`s1`执行`intern`后返回常量池中的地址，
    因此第二个输出为`true`。
    - `s3`是新创建的对象，执行`intern`后会将内容复制到常量池中再返回地址，会有两个内容相同的对象，一个在常量池中，
    一个在堆中，因此第三个输出为`false`。
    - `s4`和`s3`的情况类似，第四个输出也为`false`。但不同的是`"java"`这个字符串因为`JVM`会用到，
    它早已被系统添加到常量池中。
    - `s5`中，字面量`"xyz"`会被复制到常量池中，而`s5`是一个新的对象，因此第五个输出为`false`。
2. `JDK7`及以后：常量池现在在堆中，`intern`方法不再复制字符串实例，`String`的`intern`方法首先将尝试在常量池中查找该对象的引用，
如果找到则直接返回该对象在常量池中的引用地址。
    - `s1`是新创建的对象，`s2`存在于常量池中，因此第一个输出为`false`；当`s1`执行`intern`后返回常量池中的地址，
    因此第二个输出为`true`。
    - `s3`是新创建的对象，执行`intern`后会将引用复制到常量池中再返回引用，只有一个对象，因此第三个输出为`true`。
    - `s4`是新创建的对象，但`"java"`因为被`JVM`使用，已经存在于常量池中，`intern`返回常量池的引用和`s4`不同，
    因此输出为`false`。
    - `s5`中，字面量`"xyz"`的引用会被复制到常量池中，而`s5`是一个新的对象，因此第五个输出为`false`。

 
[method-area]: 方法区.md
[class]: ../../../res/img/const-pool-class.png
[constant-fold]: 常量折叠.md
[utf8-info]: ../../../res/img/const-pool-utf8-info.jpeg
[string-info]: ../../../res/img/const-pool-string-info.jpeg
[test]: ../../../test/java_/lang/StringTest.java

<b id="f1">\[1\]</b> 参考 https://cloud.tencent.com/developer/article/1450501。 [↩](#a1)